<?xml version="1.0" encoding="utf-8"?>
<class id="fa831f0d-9365-471c-8c32-b94704690f60" type="Folder" typeId="3407a825-1331-4f3f-89a4-901903ed97ce">
  <name>Templates</name>
  <display>Templates</display>
  <isAbstract>false</isAbstract>
  <sort-children>by-type-then-by-name</sort-children>
  <genericTypes />
  <isMapped>false</isMapped>
  <parentFolderId>5ee0a080-8d9e-4256-87e6-9b660bb9a34a</parentFolderId>
  <packageId>8b21b6d3-b2d0-455d-872b-fc9d873665ff</packageId>
  <packageName>Intent.Modules.Web</packageName>
  <stereotypes>
    <stereotype stereotypeDefinitionId="61132551-825d-4c6e-b9f1-0f95249d08d4" name="Folder Options">
      <addedByDefault>true</addedByDefault>
      <definitionPackageName>Intent.VisualStudio.Projects</definitionPackageName>
      <definitionPackageId>a0636ab7-d3a1-430b-9609-11a18aa3cc7f</definitionPackageId>
      <properties>
        <property name="4bfbefd0-d22e-4ca0-9723-92ae273feca4" display="Namespace Provider" value="true" isActive="true" />
      </properties>
    </stereotype>
  </stereotypes>
  <metadata />
  <childElements>
    <childElement id="bd5c0fde-2d02-4732-8cc5-1adcef38445b" type="Template Output" typeId="d421c322-7a51-4094-89fa-e5d8a0a97b27">
      <name>Intent.ModuleBuilder.Html.Templates.HtmlFileTemplate</name>
      <display>Intent.ModuleBuilder.Html.Templates.HtmlFileTemplate</display>
      <externalReference>Intent.ModuleBuilder.Html</externalReference>
      <isAbstract>false</isAbstract>
      <genericTypes />
      <isMapped>false</isMapped>
      <parentFolderId>fa831f0d-9365-471c-8c32-b94704690f60</parentFolderId>
      <packageId>8b21b6d3-b2d0-455d-872b-fc9d873665ff</packageId>
      <packageName>Intent.Modules.Web</packageName>
      <stereotypes />
      <metadata>
        <entry key="status" value="assigned" />
      </metadata>
      <childElements />
    </childElement>
    <childElement id="3c07146e-6f7e-4301-a3c6-60727cf8635e" type="Template Output" typeId="d421c322-7a51-4094-89fa-e5d8a0a97b27">
      <name>Intent.ModuleBuilder.Html.Templates.HtmlFileTemplatePartial</name>
      <display>Intent.ModuleBuilder.Html.Templates.HtmlFileTemplatePartial</display>
      <externalReference>Intent.ModuleBuilder.Html</externalReference>
      <isAbstract>false</isAbstract>
      <genericTypes />
      <isMapped>false</isMapped>
      <parentFolderId>fa831f0d-9365-471c-8c32-b94704690f60</parentFolderId>
      <packageId>8b21b6d3-b2d0-455d-872b-fc9d873665ff</packageId>
      <packageName>Intent.Modules.Web</packageName>
      <stereotypes />
      <metadata>
        <entry key="status" value="assigned" />
      </metadata>
      <childElements />
    </childElement>
    <childElement id="2139265c-472f-47f0-9a7f-69bd9c5defd9" type="Template Output" typeId="d421c322-7a51-4094-89fa-e5d8a0a97b27">
      <name>Intent.ModuleBuilder.ProjectItemTemplate.Partial</name>
      <display>Intent.ModuleBuilder.ProjectItemTemplate.Partial</display>
      <externalReference>Intent.ModuleBuilder</externalReference>
      <isAbstract>false</isAbstract>
      <genericTypes />
      <isMapped>false</isMapped>
      <parentFolderId>fa831f0d-9365-471c-8c32-b94704690f60</parentFolderId>
      <packageId>8b21b6d3-b2d0-455d-872b-fc9d873665ff</packageId>
      <packageName>Intent.Modules.Web</packageName>
      <stereotypes />
      <metadata>
        <entry key="status" value="assigned" />
      </metadata>
      <childElements />
    </childElement>
    <childElement id="faad50fa-d2c7-4ef1-b03d-9f40630f41c2" type="Template Output" typeId="d421c322-7a51-4094-89fa-e5d8a0a97b27">
      <name>Intent.ModuleBuilder.ProjectItemTemplate.T4Template.PreProcessed</name>
      <display>Intent.ModuleBuilder.ProjectItemTemplate.T4Template.PreProcessed</display>
      <externalReference>Intent.ModuleBuilder</externalReference>
      <isAbstract>false</isAbstract>
      <genericTypes />
      <isMapped>false</isMapped>
      <parentFolderId>fa831f0d-9365-471c-8c32-b94704690f60</parentFolderId>
      <packageId>8b21b6d3-b2d0-455d-872b-fc9d873665ff</packageId>
      <packageName>Intent.Modules.Web</packageName>
      <stereotypes />
      <metadata>
        <entry key="status" value="assigned" />
      </metadata>
      <childElements />
    </childElement>
    <childElement id="32293790-af88-4723-b69b-af8b0c546fa7" type="Template Output" typeId="d421c322-7a51-4094-89fa-e5d8a0a97b27">
      <name>Intent.ModuleBuilder.TemplateRegistration.Custom</name>
      <display>Intent.ModuleBuilder.TemplateRegistration.Custom</display>
      <externalReference>Intent.ModuleBuilder</externalReference>
      <isAbstract>false</isAbstract>
      <genericTypes />
      <isMapped>false</isMapped>
      <parentFolderId>fa831f0d-9365-471c-8c32-b94704690f60</parentFolderId>
      <packageId>8b21b6d3-b2d0-455d-872b-fc9d873665ff</packageId>
      <packageName>Intent.Modules.Web</packageName>
      <stereotypes />
      <metadata>
        <entry key="status" value="assigned" />
      </metadata>
      <childElements />
    </childElement>
    <childElement id="b2033238-a952-4e69-a1cb-d0e5d82e3bdd" type="Template Output" typeId="d421c322-7a51-4094-89fa-e5d8a0a97b27">
      <name>Intent.ModuleBuilder.TemplateRegistration.FilePerModel</name>
      <display>Intent.ModuleBuilder.TemplateRegistration.FilePerModel</display>
      <externalReference>Intent.ModuleBuilder</externalReference>
      <isAbstract>false</isAbstract>
      <genericTypes />
      <isMapped>false</isMapped>
      <parentFolderId>fa831f0d-9365-471c-8c32-b94704690f60</parentFolderId>
      <packageId>8b21b6d3-b2d0-455d-872b-fc9d873665ff</packageId>
      <packageName>Intent.Modules.Web</packageName>
      <stereotypes />
      <metadata>
        <entry key="status" value="assigned" />
      </metadata>
      <childElements />
    </childElement>
    <childElement id="7a8715c3-cc16-49ed-acf3-2f2985cb4b54" type="Template Output" typeId="d421c322-7a51-4094-89fa-e5d8a0a97b27">
      <name>Intent.ModuleBuilder.TemplateRegistration.SingleFileListModel</name>
      <display>Intent.ModuleBuilder.TemplateRegistration.SingleFileListModel</display>
      <externalReference>Intent.ModuleBuilder</externalReference>
      <isAbstract>false</isAbstract>
      <genericTypes />
      <isMapped>false</isMapped>
      <parentFolderId>fa831f0d-9365-471c-8c32-b94704690f60</parentFolderId>
      <packageId>8b21b6d3-b2d0-455d-872b-fc9d873665ff</packageId>
      <packageName>Intent.Modules.Web</packageName>
      <stereotypes />
      <metadata>
        <entry key="status" value="assigned" />
      </metadata>
      <childElements />
    </childElement>
    <childElement id="b7d5e513-b670-4d24-b80b-0e7695923924" type="Template Output" typeId="d421c322-7a51-4094-89fa-e5d8a0a97b27">
      <name>Intent.ModuleBuilder.TemplateRegistration.SingleFileNoModel</name>
      <display>Intent.ModuleBuilder.TemplateRegistration.SingleFileNoModel</display>
      <externalReference>Intent.ModuleBuilder</externalReference>
      <isAbstract>false</isAbstract>
      <genericTypes />
      <isMapped>false</isMapped>
      <parentFolderId>fa831f0d-9365-471c-8c32-b94704690f60</parentFolderId>
      <packageId>8b21b6d3-b2d0-455d-872b-fc9d873665ff</packageId>
      <packageName>Intent.Modules.Web</packageName>
      <stereotypes />
      <metadata>
        <entry key="status" value="assigned" />
      </metadata>
      <childElements />
    </childElement>
    <childElement id="36c3597d-b320-4c38-b676-1c3e16686331" type="Template Output" typeId="d421c322-7a51-4094-89fa-e5d8a0a97b27">
      <name>Intent.ModuleBuilder.Templates.FileTemplateStringInterpolation</name>
      <display>Intent.ModuleBuilder.Templates.FileTemplateStringInterpolation</display>
      <externalReference>Intent.ModuleBuilder</externalReference>
      <isAbstract>false</isAbstract>
      <genericTypes />
      <isMapped>false</isMapped>
      <parentFolderId>fa831f0d-9365-471c-8c32-b94704690f60</parentFolderId>
      <packageId>8b21b6d3-b2d0-455d-872b-fc9d873665ff</packageId>
      <packageName>Intent.Modules.Web</packageName>
      <stereotypes />
      <metadata>
        <entry key="status" value="assigned" />
      </metadata>
      <childElements />
    </childElement>
    <childElement id="d9b57969-6425-4728-9edf-dd2739d18e17" type="Template Output" typeId="d421c322-7a51-4094-89fa-e5d8a0a97b27">
      <name>Intent.ModuleBuilder.Templates.FileTemplateT4</name>
      <display>Intent.ModuleBuilder.Templates.FileTemplateT4</display>
      <externalReference>Intent.ModuleBuilder</externalReference>
      <isAbstract>false</isAbstract>
      <genericTypes />
      <isMapped>false</isMapped>
      <parentFolderId>fa831f0d-9365-471c-8c32-b94704690f60</parentFolderId>
      <packageId>8b21b6d3-b2d0-455d-872b-fc9d873665ff</packageId>
      <packageName>Intent.Modules.Web</packageName>
      <stereotypes />
      <metadata>
        <entry key="status" value="assigned" />
      </metadata>
      <childElements />
    </childElement>
    <childElement id="8d7dfb6c-53e0-4609-8c06-1e0b95e666a7" type="Template Output" typeId="d421c322-7a51-4094-89fa-e5d8a0a97b27">
      <name>Intent.ModuleBuilder.Templates.StaticContentTemplateRegistration</name>
      <display>Intent.ModuleBuilder.Templates.StaticContentTemplateRegistration</display>
      <externalReference>Intent.ModuleBuilder</externalReference>
      <isAbstract>false</isAbstract>
      <genericTypes />
      <isMapped>false</isMapped>
      <parentFolderId>fa831f0d-9365-471c-8c32-b94704690f60</parentFolderId>
      <packageId>8b21b6d3-b2d0-455d-872b-fc9d873665ff</packageId>
      <packageName>Intent.Modules.Web</packageName>
      <stereotypes />
      <metadata>
        <entry key="status" value="assigned" />
      </metadata>
      <childElements />
    </childElement>
    <childElement id="ad9960fc-72d6-4ae2-a796-9fa3e55f2e8e" type="Template Output" typeId="d421c322-7a51-4094-89fa-e5d8a0a97b27">
      <name>Intent.ModuleBuilder.Templates.TemplateDecoratorContract</name>
      <display>Intent.ModuleBuilder.Templates.TemplateDecoratorContract</display>
      <externalReference>Intent.ModuleBuilder</externalReference>
      <isAbstract>false</isAbstract>
      <genericTypes />
      <isMapped>false</isMapped>
      <parentFolderId>fa831f0d-9365-471c-8c32-b94704690f60</parentFolderId>
      <packageId>8b21b6d3-b2d0-455d-872b-fc9d873665ff</packageId>
      <packageName>Intent.Modules.Web</packageName>
      <stereotypes />
      <metadata>
        <entry key="status" value="assigned" />
      </metadata>
      <childElements />
    </childElement>
    <childElement id="a3660a54-7e82-4ad4-b827-7ded0b1454c1" type="Template Output" typeId="d421c322-7a51-4094-89fa-e5d8a0a97b27">
      <name>Intent.ModuleBuilder.Templates.TemplateExtensions</name>
      <display>Intent.ModuleBuilder.Templates.TemplateExtensions</display>
      <externalReference>Intent.ModuleBuilder</externalReference>
      <isAbstract>false</isAbstract>
      <genericTypes />
      <isMapped>false</isMapped>
      <parentFolderId>fa831f0d-9365-471c-8c32-b94704690f60</parentFolderId>
      <packageId>8b21b6d3-b2d0-455d-872b-fc9d873665ff</packageId>
      <packageName>Intent.Modules.Web</packageName>
      <stereotypes />
      <metadata>
        <entry key="status" value="assigned" />
      </metadata>
      <childElements />
    </childElement>
    <childElement id="8a25776b-f487-4031-82e8-c91065f170bf" type="Template Output" typeId="d421c322-7a51-4094-89fa-e5d8a0a97b27">
      <name>Intent.ModuleBuilder.TypeScript.Templates.TypescriptTemplatePartial</name>
      <display>Intent.ModuleBuilder.TypeScript.Templates.TypescriptTemplatePartial</display>
      <externalReference>Intent.ModuleBuilder.TypeScript</externalReference>
      <isAbstract>false</isAbstract>
      <genericTypes />
      <isMapped>false</isMapped>
      <parentFolderId>fa831f0d-9365-471c-8c32-b94704690f60</parentFolderId>
      <packageId>8b21b6d3-b2d0-455d-872b-fc9d873665ff</packageId>
      <packageName>Intent.Modules.Web</packageName>
      <stereotypes />
      <metadata>
        <entry key="status" value="assigned" />
      </metadata>
      <childElements />
    </childElement>
    <childElement id="8834c267-e67d-44bb-9691-362e45faf4d4" type="Template Output" typeId="d421c322-7a51-4094-89fa-e5d8a0a97b27">
      <name>Intent.ModuleBuilder.TypeScript.Templates.TypescriptTemplateStringInterpolation</name>
      <display>Intent.ModuleBuilder.TypeScript.Templates.TypescriptTemplateStringInterpolation</display>
      <externalReference>Intent.ModuleBuilder.TypeScript</externalReference>
      <isAbstract>false</isAbstract>
      <genericTypes />
      <isMapped>false</isMapped>
      <parentFolderId>fa831f0d-9365-471c-8c32-b94704690f60</parentFolderId>
      <packageId>8b21b6d3-b2d0-455d-872b-fc9d873665ff</packageId>
      <packageName>Intent.Modules.Web</packageName>
      <stereotypes />
      <metadata>
        <entry key="status" value="assigned" />
      </metadata>
      <childElements />
    </childElement>
    <childElement id="b6a0cdc2-02da-4833-b1ff-0fc6fc4e5f68" type="Template Output" typeId="d421c322-7a51-4094-89fa-e5d8a0a97b27">
      <name>Intent.ModuleBuilder.TypeScript.Templates.TypescriptTemplateT4</name>
      <display>Intent.ModuleBuilder.TypeScript.Templates.TypescriptTemplateT4</display>
      <externalReference>Intent.ModuleBuilder.TypeScript</externalReference>
      <isAbstract>false</isAbstract>
      <genericTypes />
      <isMapped>false</isMapped>
      <parentFolderId>fa831f0d-9365-471c-8c32-b94704690f60</parentFolderId>
      <packageId>8b21b6d3-b2d0-455d-872b-fc9d873665ff</packageId>
      <packageName>Intent.Modules.Web</packageName>
      <stereotypes />
      <metadata>
        <entry key="status" value="assigned" />
      </metadata>
      <childElements />
    </childElement>
    <childElement id="1661602d-b102-444f-a8ef-05334bc45c37" type="Template Output" typeId="d421c322-7a51-4094-89fa-e5d8a0a97b27">
      <name>ModuleBuilder.Html.Templates.HtmlFileTemplate.T4Template.PreProcessed</name>
      <display>ModuleBuilder.Html.Templates.HtmlFileTemplate.T4Template.PreProcessed</display>
      <externalReference>Intent.ModuleBuilder.Html</externalReference>
      <isAbstract>false</isAbstract>
      <genericTypes />
      <isMapped>false</isMapped>
      <parentFolderId>fa831f0d-9365-471c-8c32-b94704690f60</parentFolderId>
      <packageId>8b21b6d3-b2d0-455d-872b-fc9d873665ff</packageId>
      <packageName>Intent.Modules.Web</packageName>
      <stereotypes />
      <metadata>
        <entry key="status" value="assigned" />
      </metadata>
      <childElements />
    </childElement>
    <childElement id="5de2ed68-e752-41dc-993a-66bdadf41e46" type="Template Output" typeId="d421c322-7a51-4094-89fa-e5d8a0a97b27">
      <name>ModuleBuilder.Typescript.Templates.TypescriptTemplate.PreProcessT4</name>
      <display>ModuleBuilder.Typescript.Templates.TypescriptTemplate.PreProcessT4</display>
      <externalReference>Intent.ModuleBuilder.TypeScript</externalReference>
      <isAbstract>false</isAbstract>
      <genericTypes />
      <isMapped>false</isMapped>
      <parentFolderId>fa831f0d-9365-471c-8c32-b94704690f60</parentFolderId>
      <packageId>8b21b6d3-b2d0-455d-872b-fc9d873665ff</packageId>
      <packageName>Intent.Modules.Web</packageName>
      <stereotypes />
      <metadata>
        <entry key="status" value="assigned" />
      </metadata>
      <childElements />
    </childElement>
  </childElements>
</class>