<?xml version="1.0" encoding="utf-8"?>
<class id="89213547-6fd5-459e-b819-274917b11101" type="Folder" typeId="4d95d53a-8855-4f35-aa82-e312643f5c5f">
  <name>Model</name>
  <display>Model</display>
  <isAbstract>false</isAbstract>
  <order>6</order>
  <genericTypes />
  <isMapped>false</isMapped>
  <parentFolderId>a3deb341-dd4e-4f7f-99f5-2f198c1c251c</parentFolderId>
  <packageId>a3deb341-dd4e-4f7f-99f5-2f198c1c251c</packageId>
  <packageName>Intent.Angular</packageName>
  <stereotypes />
  <childElements />
</class>